pykusto/__init__.py
pykusto/_src/__init__.py
pykusto/_src/client.py
pykusto/_src/client_base.py
pykusto/_src/enums.py
pykusto/_src/expressions.py
pykusto/_src/functions.py
pykusto/_src/item_fetcher.py
pykusto/_src/keywords.py
pykusto/_src/kql_converters.py
pykusto/_src/logger.py
pykusto/_src/pyspark_client.py
pykusto/_src/query.py
pykusto/_src/type_utils.py
pykusto/_src/udf.py
pykusto-0.2.0.dist-info/LICENSE
pykusto-0.2.0.dist-info/METADATA
pykusto-0.2.0.dist-info/WHEEL
pykusto-0.2.0.dist-info/top_level.txt
pykusto-0.2.0.dist-info/RECORD
