Metadata-Version: 2.1
Name: pykusto
Version: 0.2.0
Summary: Advanced python SDK for Azure Data Explorer
Home-page: https://github.com/Azure/pykusto
Author: Microsoft Corporation
Author-email: yomost@microsoft.com
License: MIT License
Keywords: kusto azure-data-explorer client library query
Platform: UNKNOWN
Classifier: Development Status :: 3 - Alpha
Classifier: Intended Audience :: Developers
Classifier: Topic :: Software Development
Classifier: License :: OSI Approved :: MIT License
Classifier: Programming Language :: Python :: 3.6
Classifier: Programming Language :: Python :: 3.7
Classifier: Programming Language :: Python :: 3.8
Classifier: Programming Language :: Python :: 3.9
Classifier: License :: OSI Approved :: MIT License
Requires-Dist: redo (==2.0.4)
Requires-Dist: azure-kusto-data (==3.1.0)
Requires-Dist: pandas (<=1.2.4,>=0.25.0)
Provides-Extra: test
Requires-Dist: pytest ; extra == 'test'
Requires-Dist: pytest-cov ; extra == 'test'
Requires-Dist: flake8 ; extra == 'test'
Requires-Dist: typeguard ; extra == 'test'
